LICENSE
MANIFEST.in
README.md
setup.py
django_doh.egg-info/PKG-INFO
django_doh.egg-info/SOURCES.txt
django_doh.egg-info/dependency_links.txt
django_doh.egg-info/requires.txt
django_doh.egg-info/top_level.txt
doh_server/__init__.py
doh_server/apps.py
doh_server/constants.py
doh_server/dns_resolver.py
doh_server/urls.py
doh_server/utils.py
doh_server/views.py
tests/__init__.py
tests/test_dns_resolver.py
tests/test_server.py
tests/test_settings.py
tests/test_utils.py