Metadata-Version: 2.1
Name: django-doh
Version: 0.1.1
Summary: A simple Django app to serve DOH.
Home-page: https://github.com/treussart/django-doh
Author: Matthieu Treussart
Author-email: matthieu@treussart.com
License: BSD License
Platform: UNKNOWN
Classifier: Environment :: Web Environment
Classifier: Framework :: Django
Classifier: Framework :: Django :: 2.2
Classifier: License :: OSI Approved :: BSD License
Classifier: Operating System :: OS Independent
Classifier: Programming Language :: Python
Classifier: Programming Language :: Python :: 3.7
Classifier: Topic :: Internet :: WWW/HTTP
Classifier: Topic :: Internet :: Name Service (DNS)
Requires-Python: >=3.6
License-File: LICENSE
